osagent/__init__.py
osagent/agents/__init__.py
osagent/agents/agent.py
osagent/agents/audio.py
osagent/agents/main.py
osagent/agents/prompts.py
osagent/agents/accessibility_tree_wrap/__init__.py
osagent/agents/accessibility_tree_wrap/heuristic_retrieve.py
osagent/env/__init__.py
osagent/env/actions.py
osagent/env/desktop_env.py
osagent/env/controllers/__init__.py
osagent/env/controllers/python.py
osagent/env/controllers/setup.py
osagent/env/evaluators/__init__.py
osagent/env/evaluators/getters/__init__.py
osagent/env/evaluators/getters/calc.py
osagent/env/evaluators/getters/chrome.py
osagent/env/evaluators/getters/file.py
osagent/env/evaluators/getters/general.py
osagent/env/evaluators/getters/gimp.py
osagent/env/evaluators/getters/impress.py
osagent/env/evaluators/getters/info.py
osagent/env/evaluators/getters/misc.py
osagent/env/evaluators/getters/replay.py
osagent/env/evaluators/getters/vlc.py
osagent/env/evaluators/getters/vscode.py
osagent/env/evaluators/metrics/__init__.py
osagent/env/evaluators/metrics/basic_os.py
osagent/env/evaluators/metrics/chrome.py
osagent/env/evaluators/metrics/docs.py
osagent/env/evaluators/metrics/general.py
osagent/env/evaluators/metrics/gimp.py
osagent/env/evaluators/metrics/libreoffice.py
osagent/env/evaluators/metrics/others.py
osagent/env/evaluators/metrics/pdf.py
osagent/env/evaluators/metrics/slides.py
osagent/env/evaluators/metrics/table.py
osagent/env/evaluators/metrics/thunderbird.py
osagent/env/evaluators/metrics/utils.py
osagent/env/evaluators/metrics/vlc.py
osagent/env/evaluators/metrics/vscode.py
osagent/env/providers/__init__.py
osagent/env/providers/base.py
osagent/env/providers/local/__init__.py
osagent/env/providers/local/manager.py
osagent/env/providers/local/provider.py
osagent/env/server/main.py
osagent/env/server/pyxcursor.py
osagent-0.1.1.dist-info/METADATA
osagent-0.1.1.dist-info/WHEEL
osagent-0.1.1.dist-info/top_level.txt
osagent-0.1.1.dist-info/RECORD
